socpy/__init__.py
socpy/jobdesc.py
socpy/request.py
socpy/response.py
socpy/soccer.py
socpy/utils.py
socpy/data/job_desc.csv
socpy-0.0.6.dist-info/LICENSE
socpy-0.0.6.dist-info/METADATA
socpy-0.0.6.dist-info/WHEEL
socpy-0.0.6.dist-info/top_level.txt
socpy-0.0.6.dist-info/RECORD
